{
    "img_url": "data/recorded_sequences/img221.jpg",
    "frame": 221,
    "keypoints": {
        "0": [
            320.2785949707031,
            116.6751480102539,
            1.665000041325887
        ],
        "1": [
            359.4036560058594,
            194.95228576660156,
            1.6773639891867484
        ],
        "2": [
            309.8409729003906,
            196.26673889160156,
            1.7539021057688202
        ],
        "3": [
            244.58680725097656,
            238.0724334716797,
            1.7262306468877069
        ],
        "4": [
            222.39280700683594,
            183.17283630371094,
            1.690316509309285
        ],
        "5": [
            401.1825256347656,
            194.96669006347656,
            1.6991479006384718
        ],
        "6": [
            0.0,
            0.0,
            1.6773639891867484
        ],
        "7": [
            0.0,
            0.0,
            1.6732427200231959
        ],
        "8": [
            333.34246826171875,
            364.6415100097656,
            1.5996483069707175
        ],
        "9": [
            295.4383239746094,
            356.8170166015625,
            1.627908478483709
        ],
        "10": [
            274.5791320800781,
            476.9203186035156,
            1.6520475212033507
        ],
        "11": [
            0.0,
            0.0,
            1.7397720200123248
        ],
        "12": [
            375.0705261230469,
            369.86602783203125,
            1.6078908452978231
        ],
        "13": [
            0.0,
            0.0,
            1.6438048425060419
        ],
        "14": [
            0.0,
            0.0,
            1.766265913259479
        ],
        "15": [
            318.9926452636719,
            108.80232238769531,
            1.6773639891867484
        ],
        "16": [
            329.4369812011719,
            104.9049301147461,
            1.6438048425060419
        ],
        "17": [
            0.0,
            0.0,
            1.7079791515974554
        ],
        "18": [
            367.2514953613281,
            102.32544708251953,
            1.6820739709821793
        ],
        "19": [
            0.0,
            0.0,
            1.766265913259479
        ],
        "20": [
            0.0,
            0.0,
            1.766265913259479
        ],
        "21": [
            0.0,
            0.0,
            1.766265913259479
        ],
        "22": [
            0.0,
            0.0,
            1.766265913259479
        ],
        "23": [
            0.0,
            0.0,
            1.766265913259479
        ],
        "24": [
            0.0,
            0.0,
            1.7586122279344543
        ]
    }
}