{
    "img_url": "data/recorded_sequences/img245.jpg",
    "frame": 245,
    "keypoints": {
        "0": [
            330.73126220703125,
            124.49999237060547,
            1.665000041325887
        ],
        "1": [
            355.49346923828125,
            184.56179809570312,
            1.6773639891867484
        ],
        "2": [
            316.335693359375,
            188.46632385253906,
            1.7539021057688202
        ],
        "3": [
            255.06214904785156,
            204.05801391601562,
            1.7262306468877069
        ],
        "4": [
            227.610595703125,
            162.36630249023438,
            1.690316509309285
        ],
        "5": [
            390.747314453125,
            184.53082275390625,
            1.6991479006384718
        ],
        "6": [
            0.0,
            0.0,
            1.6773639891867484
        ],
        "7": [
            0.0,
            0.0,
            1.6732427200231959
        ],
        "8": [
            329.40972900390625,
            363.33807373046875,
            1.5996483069707175
        ],
        "9": [
            294.1482849121094,
            354.2129211425781,
            1.627908478483709
        ],
        "10": [
            266.79217529296875,
            476.91802978515625,
            1.6520475212033507
        ],
        "11": [
            0.0,
            0.0,
            1.7397720200123248
        ],
        "12": [
            369.85101318359375,
            369.882080078125,
            1.6078908452978231
        ],
        "13": [
            0.0,
            0.0,
            1.6438048425060419
        ],
        "14": [
            0.0,
            0.0,
            1.766265913259479
        ],
        "15": [
            328.0906982421875,
            114.03797912597656,
            1.6773639891867484
        ],
        "16": [
            346.36871337890625,
            110.11980438232422,
            1.6438048425060419
        ],
        "17": [
            0.0,
            0.0,
            1.7079791515974554
        ],
        "18": [
            371.19183349609375,
            106.21492767333984,
            1.6820739709821793
        ],
        "19": [
            0.0,
            0.0,
            1.766265913259479
        ],
        "20": [
            0.0,
            0.0,
            1.766265913259479
        ],
        "21": [
            0.0,
            0.0,
            1.766265913259479
        ],
        "22": [
            0.0,
            0.0,
            1.766265913259479
        ],
        "23": [
            0.0,
            0.0,
            1.766265913259479
        ],
        "24": [
            0.0,
            0.0,
            1.7586122279344543
        ]
    }
}