{
    "img_url": "data/recorded_sequences/img331.jpg",
    "frame": 331,
    "keypoints": {
        "0": [
            0.0,
            0.0,
            1.5216667254765828
        ],
        "1": [
            348.96514892578125,
            46.21403884887695,
            1.532966309613781
        ],
        "2": [
            251.08518981933594,
            40.96473693847656,
            1.6029155602701601
        ],
        "3": [
            192.37130737304688,
            180.5889434814453,
            1.577626228630713
        ],
        "4": [
            227.6003875732422,
            308.5135498046875,
            1.5448037981377059
        ],
        "5": [
            440.34710693359375,
            55.31757736206055,
            1.5528749296642759
        ],
        "6": [
            487.3316345214844,
            181.92555236816406,
            1.532966309613781
        ],
        "7": [
            512.1478881835938,
            287.6511535644531,
            1.5291998243301428
        ],
        "8": [
            328.08782958984375,
            299.3975524902344,
            1.461940865325098
        ],
        "9": [
            273.2737121582031,
            299.390869140625,
            1.4877682296375554
        ],
        "10": [
            0.0,
            0.0,
            1.509829236952658
        ],
        "11": [
            0.0,
            0.0,
            1.5900018781139316
        ],
        "12": [
            381.6111145019531,
            298.0710754394531,
            1.4694738358923745
        ],
        "13": [
            0.0,
            0.0,
            1.502296138099098
        ],
        "14": [
            0.0,
            0.0,
            1.6142150161210749
        ],
        "15": [
            0.0,
            0.0,
            1.532966309613781
        ],
        "16": [
            0.0,
            0.0,
            1.502296138099098
        ],
        "17": [
            0.0,
            0.0,
            1.5609459329045625
        ],
        "18": [
            0.0,
            0.0,
            1.5372708275704294
        ],
        "19": [
            0.0,
            0.0,
            1.6142150161210749
        ],
        "20": [
            0.0,
            0.0,
            1.6142150161210749
        ],
        "21": [
            0.0,
            0.0,
            1.6142150161210749
        ],
        "22": [
            0.0,
            0.0,
            1.6142150161210749
        ],
        "23": [
            0.0,
            0.0,
            1.6142150161210749
        ],
        "24": [
            0.0,
            0.0,
            1.607220206513092
        ]
    }
}