{
    "img_url": "data/recorded_sequences/img69.jpg",
    "frame": 69,
    "keypoints": {
        "0": [
            346.3841552734375,
            107.54824829101562,
            1.7140001058578491
        ],
        "1": [
            339.84576416015625,
            183.1834716796875,
            1.7350001335144043
        ],
        "2": [
            277.1929931640625,
            180.6099090576172,
            1.7570000886917114
        ],
        "3": [
            244.51840209960938,
            266.7176513671875,
            1.727000117301941
        ],
        "4": [
            227.62289428710938,
            349.01287841796875,
            1.5870001316070557
        ],
        "5": [
            402.5214538574219,
            185.84478759765625,
            1.7570000886917114
        ],
        "6": [
            476.89605712890625,
            236.77032470703125,
            1.6730000972747803
        ],
        "7": [
            496.494384765625,
            150.54177856445312,
            1.6880000829696655
        ],
        "8": [
            338.5008850097656,
            365.94097900390625,
            1.4970000982284546
        ],
        "9": [
            290.2391662597656,
            363.3440856933594,
            1.5160000324249268
        ],
        "10": [
            278.4797668457031,
            476.923095703125,
            1.4390000104904175
        ],
        "11": [
            0.0,
            0.0,
            0.0
        ],
        "12": [
            381.617431640625,
            368.5702209472656,
            1.5260000228881836
        ],
        "13": [
            377.7120666503906,
            476.9143981933594,
            1.4540001153945923
        ],
        "14": [
            0.0,
            0.0,
            0.0
        ],
        "15": [
            334.6277160644531,
            95.77386474609375,
            1.7300001382827759
        ],
        "16": [
            359.3644714355469,
            97.04723358154297,
            1.7300001382827759
        ],
        "17": [
            317.67425537109375,
            102.31574249267578,
            1.78000009059906
        ],
        "18": [
            372.45330810546875,
            106.21136474609375,
            1.783000111579895
        ],
        "19": [
            0.0,
            0.0,
            0.0
        ],
        "20": [
            0.0,
            0.0,
            0.0
        ],
        "21": [
            0.0,
            0.0,
            0.0
        ],
        "22": [
            0.0,
            0.0,
            0.0
        ],
        "23": [
            0.0,
            0.0,
            0.0
        ],
        "24": [
            0.0,
            0.0,
            0.0
        ]
    }
}