{
    "img_url": "data/recorded_sequences/img86.jpg",
    "frame": 86,
    "keypoints": {
        "0": [
            343.7640686035156,
            112.73111724853516,
            1.752000093460083
        ],
        "1": [
            337.2472839355469,
            181.92398071289062,
            1.7680001258850098
        ],
        "2": [
            279.8085021972656,
            179.32809448242188,
            1.7440000772476196
        ],
        "3": [
            262.8551940917969,
            243.25686645507812,
            1.4620000123977661
        ],
        "4": [
            0.0,
            0.0,
            0.0
        ],
        "5": [
            390.7237548828125,
            183.24087524414062,
            1.1880000829696655
        ],
        "6": [
            422.03228759765625,
            225.0008087158203,
            1.4470000267028809
        ],
        "7": [
            420.73236083984375,
            184.52462768554688,
            0.0
        ],
        "8": [
            339.82177734375,
            359.4114990234375,
            1.5140000581741333
        ],
        "9": [
            296.7260437011719,
            358.13214111328125,
            1.53000009059906
        ],
        "10": [
            278.53082275390625,
            476.92242431640625,
            1.4490001201629639
        ],
        "11": [
            0.0,
            0.0,
            0.0
        ],
        "12": [
            381.64007568359375,
            360.7212219238281,
            1.558000087738037
        ],
        "13": [
            377.68682861328125,
            476.9114990234375,
            1.4620000123977661
        ],
        "14": [
            0.0,
            0.0,
            0.0
        ],
        "15": [
            331.9954528808594,
            101.00590515136719,
            1.7740000486373901
        ],
        "16": [
            355.5276794433594,
            103.59049224853516,
            1.7660000324249268
        ],
        "17": [
            316.35943603515625,
            108.87671661376953,
            1.815000057220459
        ],
        "18": [
            369.8988037109375,
            112.75157165527344,
            1.842000126838684
        ],
        "19": [
            0.0,
            0.0,
            0.0
        ],
        "20": [
            0.0,
            0.0,
            0.0
        ],
        "21": [
            0.0,
            0.0,
            0.0
        ],
        "22": [
            0.0,
            0.0,
            0.0
        ],
        "23": [
            0.0,
            0.0,
            0.0
        ],
        "24": [
            0.0,
            0.0,
            0.0
        ]
    }
}